LICENSE
setup.py
stat_box/__init__.py
stat_box/statistic.py
stat_box/time_series.py
stat_box.egg-info/PKG-INFO
stat_box.egg-info/SOURCES.txt
stat_box.egg-info/dependency_links.txt
stat_box.egg-info/requires.txt
stat_box.egg-info/top_level.txt