Metadata-Version: 2.1
Name: stat-box
Version: 0.1.0
Summary: Convinient statistical description of dataframes and time series.
Home-page: https://gitlab.com/dmatryus.sqrt49/stat_box
Author: dmatryus
Author-email: dmatryus.sqrt49@yandex.ru
License: GPLv3
Keywords: STATICS,TIME_SERIES
Platform: UNKNOWN
